srv_hijacker/__init__.py
srv_hijacker/srv_hijacker.py
tests/__init__.py
tests/test_srv_hijacker.py
srv_hijacker-0.0.7.dist-info/METADATA
srv_hijacker-0.0.7.dist-info/WHEEL
srv_hijacker-0.0.7.dist-info/top_level.txt
srv_hijacker-0.0.7.dist-info/RECORD
