Metadata-Version: 2.1
Name: srv-hijacker
Version: 0.0.7
Summary: Patch urllib3 to query a certain DNS server for SRV records
Home-page: https://github.com/rohitpaulk/srv_hijacker
Author: Paul Kuruvilla
Author-email: paul.kuruvilla@shuttl.com
License: MIT
Platform: UNKNOWN
Classifier: Programming Language :: Python :: 3.7
Requires-Dist: dnspython
